u2_adapter/__init__.py
u2_adapter/ios_adapter.py
u2_adapter-0.0.1.dist-info/licenses/LICENSE
u2_adapter-0.0.1.dist-info/METADATA
u2_adapter-0.0.1.dist-info/WHEEL
u2_adapter-0.0.1.dist-info/top_level.txt
u2_adapter-0.0.1.dist-info/RECORD
