Metadata-Version: 2.4
Name: u2-adapter
Version: 0.0.1
Summary: A universal automation adapter providing a uiautomator2-compatible interface for iOS (WDA) and potentially PC platforms.
Author-email: hexin <hexinpy@gmail.com>
License: MIT
Project-URL: Homepage, https://github.com/bodphi/u2_adapter
Project-URL: Bug Tracker, https://github.com/bodphi/u2_adapter/issues
Classifier: Programming Language :: Python :: 3
Classifier: License :: OSI Approved :: MIT License
Classifier: Operating System :: OS Independent
Requires-Python: >=3.7
License-File: LICENSE
Requires-Dist: facebook-wda
Dynamic: license-file
